potassium/__init__.py
potassium/exceptions.py
potassium/hooks.py
potassium/potassium.py
potassium/status.py
potassium/store.py
potassium/store_test.py
potassium/types.py
potassium/worker.py
potassium-0.5.0.dist-info/LICENSE
potassium-0.5.0.dist-info/METADATA
potassium-0.5.0.dist-info/WHEEL
potassium-0.5.0.dist-info/top_level.txt
potassium-0.5.0.dist-info/RECORD
