Metadata-Version: 2.1
Name: potassium
Version: 0.5.0
Summary: The potassium package is a flask-like HTTP server for serving large AI models
Home-page: https://www.banana.dev
Author: Erik Dunteman
Author-email: erik@banana.dev
License: Apache License 2.0
Keywords: Banana server,HTTP server,Banana,Framework
Classifier: Development Status :: 3 - Alpha
Classifier: Intended Audience :: Developers
Classifier: Topic :: Software Development :: Build Tools
Classifier: License :: OSI Approved :: MIT License
Classifier: Programming Language :: Python :: 3.7
Classifier: Programming Language :: Python :: 3.8
License-File: LICENSE
Requires-Dist: Flask
Requires-Dist: requests
Requires-Dist: termcolor
Requires-Dist: redis
Requires-Dist: boto3
